neuralwatermark/__init__.py
neuralwatermark/neuralwatermark.py
neuralwatermark-0.1.1.dist-info/WHEEL
neuralwatermark-0.1.1.dist-info/METADATA
neuralwatermark-0.1.1.dist-info/RECORD
